calendar_app_package/__init__.py
calendar_app_package/calendar_api.py
calendar_app_package/main.py
calendar_app_package/manager.py
calendar_app_package/task.py
example_package_higgs_demo_13-0.1.0.dist-info/licenses/LICENSE
example_package_higgs_demo_13-0.1.0.dist-info/METADATA
example_package_higgs_demo_13-0.1.0.dist-info/WHEEL
example_package_higgs_demo_13-0.1.0.dist-info/entry_points.txt
example_package_higgs_demo_13-0.1.0.dist-info/top_level.txt
example_package_higgs_demo_13-0.1.0.dist-info/RECORD
