Metadata-Version: 2.4
Name: example-package-Higgs-demo-13
Version: 0.1.0
Summary: Google‑Calendar powered CLI task scheduler
Author-email: Andrew Higgins <ahiggin9@emich.edu>
License: MIT License
Project-URL: Homepage, https://github.com/COSC381-2025Winter/lab13-sprint-full-stack-slop-llc
Project-URL: Issues, https://github.com/COSC381-2025Winter/lab13-sprint-full-stack-slop-llc/issues
Classifier: Programming Language :: Python :: 3
Classifier: Programming Language :: Python :: 3 :: Only
Classifier: Operating System :: OS Independent
Classifier: License :: OSI Approved :: MIT License
Requires-Python: >=3.9
License-File: LICENSE
Requires-Dist: google-api-python-client>=2.126.0
Requires-Dist: google-auth-httplib2>=0.2
Requires-Dist: google-auth-oauthlib>=1.2.0
Requires-Dist: typer[all]>=0.9
Provides-Extra: dev
Requires-Dist: pytest; extra == "dev"
Requires-Dist: pytest-cov; extra == "dev"
Requires-Dist: ruff; extra == "dev"
Requires-Dist: black; extra == "dev"
Requires-Dist: python-dotenv; extra == "dev"
Dynamic: license-file
